ode_composer/__init__.py
ode_composer/database.py
ode_composer/dictionary_builder.py
ode_composer/errors.py
ode_composer/linear_model.py
ode_composer/measurements_generator.py
ode_composer/sbl.py
ode_composer/signal_preprocessor.py
ode_composer/simulator.py
ode_composer/statespace_model.py
ode_composer/util.py
ode_composer-0.2.2.dist-info/METADATA
ode_composer-0.2.2.dist-info/WHEEL
ode_composer-0.2.2.dist-info/top_level.txt
ode_composer-0.2.2.dist-info/RECORD
