Metadata-Version: 1.0
Name: ode-composer
Version: 0.2.2
Summary: Building ODE models from data
Home-page: https://github.com/zoltuz/ode_composer_py
Author: Zoltan A Tuza
Author-email: zoltuz@gmail.com
License: MIT
Platform: UNKNOWN
